{
  "playlist_id": "PLdV3-gSGzugBwr6SSacLJa1Aq36qSJez6",
  "playlist_url": "https://youtube.com/playlist?list=PLdV3-gSGzugBwr6SSacLJa1Aq36qSJez6",
  "videos": {
    "1": {
      "video_id": "mEadaN91mzs",
      "url": "https://youtu.be/mEadaN91mzs",
      "title": "[Week 02] 01. Blender 다운로드",
      "file": "01_blender_download.mp4"
    },
    "2": {
      "video_id": "5H7dRAX8fes",
      "url": "https://youtu.be/5H7dRAX8fes",
      "title": "[Week 02] 02. Blender 설치하기",
      "file": "02_blender_install.mp4"
    },
    "3": {
      "video_id": "WgwkmImpftE",
      "url": "https://youtu.be/WgwkmImpftE",
      "title": "[Week 02] 03. Blender 첫 실행",
      "file": "03_blender_opening.mp4"
    },
    "4": {
      "video_id": "56u2U9ntRbs",
      "url": "https://youtu.be/56u2U9ntRbs",
      "title": "[Week 02] 04. 인터페이스 소개",
      "file": "04_blender_interface.mp4"
    },
    "5": {
      "video_id": "vq66vXMSLfE",
      "url": "https://youtu.be/vq66vXMSLfE",
      "title": "[Week 02] 05. 인터페이스 심화",
      "file": "05_blender_interface_2.mp4"
    },
    "6": {
      "video_id": "k_QiQvA-LI8",
      "url": "https://youtu.be/k_QiQvA-LI8",
      "title": "[Week 02] 06. 도구상자 (Toolbox)",
      "file": "06_blender_toolbox.mp4"
    },
    "7": {
      "video_id": "GhVUEwAtTBw",
      "url": "https://youtu.be/GhVUEwAtTBw",
      "title": "[Week 02] 07. 오브젝트 추가 (Add Object)",
      "file": "07_blender_add_object.mp4"
    },
    "8": {
      "video_id": "3hoBwXfcOCA",
      "url": "https://youtu.be/3hoBwXfcOCA",
      "title": "[Week 02] 08. 오브젝트 편집 (Object Edit)",
      "file": "08_blender_object_edit.mp4"
    },
    "9": {
      "video_id": "N8ug4bgh1-E",
      "url": "https://youtu.be/N8ug4bgh1-E",
      "title": "[Week 02] 09. Tab 키로 모드 전환",
      "file": "09_blender_tab key use.mp4"
    },
    "10": {
      "video_id": "L1viZ4OmB3o",
      "url": "https://youtu.be/L1viZ4OmB3o",
      "title": "[Week 02] 10. Extrude & Inset",
      "file": "10_blender_extrude_inset.mp4"
    },
    "11": {
      "video_id": "s5X3NVO2izU",
      "url": "https://youtu.be/s5X3NVO2izU",
      "title": "[Week 02] 11. Bevel 도구",
      "file": "11_blender_bevel.mp4"
    },
    "12": {
      "video_id": "PudArEwBAvc",
      "url": "https://youtu.be/PudArEwBAvc",
      "title": "[Week 02] 12. Loop Cut 기초",
      "file": "12_blender_loopcut.mp4"
    },
    "13": {
      "video_id": "6f0EgaKuUcc",
      "url": "https://youtu.be/6f0EgaKuUcc",
      "title": "[Week 02] 13. Loop Cut 활용",
      "file": "13_blender_loopcut_2.mp4"
    },
    "14": {
      "status": "PENDING - upload limit exceeded, retry later",
      "title": "[Week 02] 14. Knife 도구",
      "file": "14_blender_knife.mp4"
    }
  }
}
